finalsa/sqs/client/__init__.py
finalsa/sqs/client/clients/Client.py
finalsa/sqs/client/clients/__init__.py
finalsa/sqs/client/exceptions/SqsException.py
finalsa/sqs/client/exceptions/__init__.py
finalsa/sqs/client/interfaces/SqsService.py
finalsa/sqs/client/interfaces/__init__.py
finalsa/sqs/client/tests/Client.py
finalsa/sqs/client/tests/__init__.py
finalsa_sqs_client-2.1.1.dist-info/METADATA
finalsa_sqs_client-2.1.1.dist-info/WHEEL
finalsa_sqs_client-2.1.1.dist-info/licenses/LICENSE.md
finalsa_sqs_client-2.1.1.dist-info/RECORD
