Metadata-Version: 2.4
Name: finalsa-sqs-client
Version: 2.1.1
Summary: finalsa-sqs-client is a Python package for interacting with AWS SQS queues.
Project-URL: Homepage, https://github.com/finalsa/finalsa-common-lambda
Author-email: Luis Jimenez <luis@finalsa.com>
License: MIT License
License-File: LICENSE.md
Keywords: aws,common,finalsa,lambda,utilities
Requires-Python: >=3.10
Requires-Dist: boto3>=1.40.11
Requires-Dist: finalsa-common-models>=2.0.3
Requires-Dist: finalsa-traceability>=1.0.1
Requires-Dist: orjson>=3.11.2
